{
 "name": "sys_set_tid_address",
 "sourcefile": "",
 "type": "original",
 "label": "sys_set_tid_address",
 "size": 1,
 "index": 0,
 "children": [
  {
   "name": "__task_pid_nr_ns",
   "sourcefile": "",
   "type": "original",
   "label": "__task_pid_nr_ns",
   "size": 1,
   "index": 1,
   "children": [
    {
     "name": "__fentry__",
     "sourcefile": "",
     "type": "original",
     "label": "__fentry__",
     "size": 1,
     "index": 2,
     "children": []
    }
   ]
  },
  {
   "label": "__fentry__",
   "name": "__fentry__",
   "index": 2,
   "type": "duplicate"
  }
 ]
}