{
 "type": "original",
 "sourcefile": "",
 "label": "sys_munmap",
 "size": 1,
 "name": "sys_munmap",
 "children": [
  {
   "type": "original",
   "sourcefile": "",
   "label": "profile_munmap",
   "size": 1,
   "name": "profile_munmap",
   "children": [
    {
     "type": "original",
     "sourcefile": "",
     "label": "blocking_notifier_call_chain",
     "size": 1,
     "name": "blocking_notifier_call_chain",
     "children": [
      {
       "type": "original",
       "sourcefile": "",
       "label": "__blocking_notifier_call_chain",
       "size": 1,
       "name": "__blocking_notifier_call_chain",
       "children": [
        {
         "type": "original",
         "sourcefile": "",
         "label": "notifier_call_chain",
         "size": 1,
         "name": "notifier_call_chain",
         "children": []
        }
       ]
      }
     ]
    }
   ]
  },
  {
   "type": "original",
   "sourcefile": "",
   "label": "vm_munmap",
   "size": 1,
   "name": "vm_munmap",
   "children": [
    {
     "type": "original",
     "sourcefile": "",
     "label": "down_write",
     "size": 1,
     "name": "down_write",
     "children": [
      {
       "type": "original",
       "sourcefile": "",
       "label": "_cond_resched",
       "size": 1,
       "name": "_cond_resched",
       "children": [
        {
         "type": "original",
         "sourcefile": "",
         "label": "preempt_schedule_common",
         "size": 1,
         "name": "preempt_schedule_common",
         "children": [
          {
           "type": "original",
           "sourcefile": "",
           "label": "__schedule",
           "size": 1,
           "name": "__schedule",
           "children": [
            {
             "type": "original",
             "sourcefile": "",
             "label": "finish_task_switch",
             "size": 1,
             "name": "finish_task_switch",
             "children": [
              {
               "type": "original",
               "sourcefile": "",
               "label": "__perf_event_task_sched_in",
               "size": 1,
               "name": "__perf_event_task_sched_in",
               "children": [
                {
                 "type": "original",
                 "sourcefile": "",
                 "label": "perf_event_context_sched_in",
                 "size": 1,
                 "name": "perf_event_context_sched_in",
                 "children": [
                  {
                   "type": "original",
                   "sourcefile": "",
                   "label": "perf_event_sched_in",
                   "size": 1,
                   "name": "perf_event_sched_in",
                   "children": [
                    {
                     "type": "original",
                     "sourcefile": "",
                     "label": "ctx_sched_in",
                     "size": 1,
                     "name": "ctx_sched_in",
                     "children": [
                      {
                       "type": "original",
                       "sourcefile": "",
                       "label": "group_sched_in",
                       "size": 1,
                       "name": "group_sched_in",
                       "children": [
                        {
                         "type": "original",
                         "sourcefile": "",
                         "label": "event_sched_in",
                         "size": 1,
                         "name": "event_sched_in",
                         "children": []
                        }
                       ]
                      }
                     ]
                    }
                   ]
                  },
                  {
                   "type": "original",
                   "sourcefile": "",
                   "label": "perf_ctx_unlock",
                   "size": 1,
                   "name": "perf_ctx_unlock",
                   "children": []
                  }
                 ]
                }
               ]
              }
             ]
            },
            {
             "type": "original",
             "sourcefile": "",
             "label": "rcu_note_context_switch",
             "size": 1,
             "name": "rcu_note_context_switch",
             "children": []
            },
            {
             "type": "original",
             "sourcefile": "",
             "label": "_raw_spin_lock_irq",
             "size": 1,
             "name": "_raw_spin_lock_irq",
             "children": []
            },
            {
             "type": "original",
             "sourcefile": "",
             "label": "__switch_to",
             "size": 1,
             "name": "__switch_to",
             "children": []
            },
            {
             "type": "original",
             "sourcefile": "",
             "label": "hrtimer_active",
             "size": 1,
             "name": "hrtimer_active",
             "children": []
            },
            {
             "type": "original",
             "sourcefile": "",
             "label": "__perf_event_task_sched_out",
             "size": 1,
             "name": "__perf_event_task_sched_out",
             "children": [
              {
               "type": "original",
               "sourcefile": "",
               "label": "perf_event_update_userpage",
               "size": 1,
               "name": "perf_event_update_userpage",
               "children": []
              },
              {
               "type": "original",
               "sourcefile": "",
               "label": "local_clock",
               "size": 1,
               "name": "local_clock",
               "children": []
              },
              {
               "type": "original",
               "sourcefile": "",
               "label": "ctx_sched_out",
               "size": 1,
               "name": "ctx_sched_out",
               "children": [
                {
                 "type": "original",
                 "sourcefile": "",
                 "label": "group_sched_out",
                 "size": 1,
                 "name": "group_sched_out",
                 "children": [
                  {
                   "type": "original",
                   "sourcefile": "",
                   "label": "event_sched_out",
                   "size": 1,
                   "name": "event_sched_out",
                   "children": []
                  }
                 ]
                },
                {
                 "type": "original",
                 "sourcefile": "",
                 "label": "perf_pmu_disable",
                 "size": 1,
                 "name": "perf_pmu_disable",
                 "children": []
                },
                {
                 "type": "original",
                 "sourcefile": "",
                 "label": "perf_pmu_enable",
                 "size": 1,
                 "name": "perf_pmu_enable",
                 "children": []
                }
               ]
              }
             ]
            },
            {
             "type": "original",
             "sourcefile": "",
             "label": "activate_task",
             "size": 1,
             "name": "activate_task",
             "children": [
              {
               "type": "original",
               "sourcefile": "",
               "label": "enqueue_task",
               "size": 1,
               "name": "enqueue_task",
               "children": []
              }
             ]
            },
            {
             "type": "original",
             "sourcefile": "",
             "label": "_raw_spin_lock",
             "size": 1,
             "name": "_raw_spin_lock",
             "children": []
            },
            {
             "type": "original",
             "sourcefile": "",
             "label": "ttwu_stat",
             "size": 1,
             "name": "ttwu_stat",
             "children": []
            },
            {
             "type": "original",
             "sourcefile": "",
             "label": "update_rq_clock",
             "size": 1,
             "name": "update_rq_clock",
             "children": [
              {
               "type": "original",
               "sourcefile": "",
               "label": "sched_clock_cpu",
               "size": 1,
               "name": "sched_clock_cpu",
               "children": [
                {
                 "type": "original",
                 "sourcefile": "",
                 "label": "sched_clock",
                 "size": 1,
                 "name": "sched_clock",
                 "children": []
                }
               ]
              }
             ]
            },
            {
             "type": "original",
             "sourcefile": "",
             "label": "ttwu_do_wakeup",
             "size": 1,
             "name": "ttwu_do_wakeup",
             "children": [
              {
               "type": "original",
               "sourcefile": "",
               "label": "check_preempt_curr",
               "size": 1,
               "name": "check_preempt_curr",
               "children": [
                {
                 "type": "original",
                 "sourcefile": "",
                 "label": "resched_curr",
                 "size": 1,
                 "name": "resched_curr",
                 "children": []
                }
               ]
              }
             ]
            }
           ]
          }
         ]
        }
       ]
      }
     ]
    }
   ]
  }
 ]
}