{
 "size": 1,
 "sourcefile": "",
 "name": "sys_utimes",
 "label": "sys_utimes",
 "children": [
  {
   "size": 1,
   "sourcefile": "",
   "name": "_copy_from_user",
   "label": "_copy_from_user",
   "children": [],
   "type": "original",
   "index": 2886
  },
  {
   "size": 1,
   "sourcefile": "",
   "name": "do_utimes",
   "label": "do_utimes",
   "children": [
    {
     "size": 1,
     "sourcefile": "",
     "name": "user_path_at_empty",
     "label": "user_path_at_empty",
     "children": [
      {
       "size": 1,
       "sourcefile": "",
       "name": "filename_lookup",
       "label": "filename_lookup",
       "children": [
        {
         "size": 1,
         "sourcefile": "",
         "name": "path_lookupat",
         "label": "path_lookupat",
         "children": [
          {
           "size": 1,
           "sourcefile": "",
           "name": "link_path_walk",
           "label": "link_path_walk",
           "children": [
            {
             "size": 1,
             "sourcefile": "",
             "name": "unlazy_walk",
             "label": "unlazy_walk",
             "children": [
              {
               "size": 1,
               "sourcefile": "",
               "name": "legitimize_path",
               "label": "legitimize_path",
               "children": [],
               "type": "original",
               "index": 2945
              },
              {
               "size": 1,
               "sourcefile": "",
               "name": "lockref_get_not_dead",
               "label": "lockref_get_not_dead",
               "children": [],
               "type": "original",
               "index": 2944
              },
              {
               "size": 1,
               "sourcefile": "",
               "name": "legitimize_mnt",
               "label": "legitimize_mnt",
               "children": [
                {
                 "size": 1,
                 "sourcefile": "",
                 "name": "mntput_no_expire",
                 "label": "mntput_no_expire",
                 "children": [
                  {
                   "size": 1,
                   "sourcefile": "",
                   "name": "queue_delayed_work_on",
                   "label": "queue_delayed_work_on",
                   "children": [
                    {
                     "size": 1,
                     "sourcefile": "",
                     "name": "__queue_delayed_work",
                     "label": "__queue_delayed_work",
                     "children": [
                      {
                       "size": 1,
                       "sourcefile": "",
                       "name": "delayed_work_timer_fn",
                       "label": "delayed_work_timer_fn",
                       "children": [],
                       "type": "original",
                       "index": 3126
                      },
                      {
                       "size": 1,
                       "sourcefile": "",
                       "name": "__queue_work",
                       "label": "__queue_work",
                       "children": [
                        {
                         "size": 1,
                         "sourcefile": "",
                         "name": "insert_work",
                         "label": "insert_work",
                         "children": [
                          {
                           "size": 1,
                           "sourcefile": "",
                           "name": "get_pwq",
                           "label": "get_pwq",
                           "children": [],
                           "type": "original",
                           "index": 3130
                          }
                         ],
                         "type": "original",
                         "index": 3129
                        },
                        {
                         "size": 1,
                         "sourcefile": "",
                         "name": "get_work_pool",
                         "label": "get_work_pool",
                         "children": [],
                         "type": "original",
                         "index": 3128
                        }
                       ],
                       "type": "original",
                       "index": 3127
                      },
                      {
                       "size": 1,
                       "sourcefile": "",
                       "name": "add_timer_on",
                       "label": "add_timer_on",
                       "children": [
                        {
                         "size": 1,
                         "sourcefile": "",
                         "name": "internal_add_timer",
                         "label": "internal_add_timer",
                         "children": [
                          {
                           "size": 1,
                           "sourcefile": "",
                           "name": "__internal_add_timer",
                           "label": "__internal_add_timer",
                           "children": [],
                           "type": "original",
                           "index": 3119
                          },
                          {
                           "size": 1,
                           "sourcefile": "",
                           "name": "wake_up_nohz_cpu",
                           "label": "wake_up_nohz_cpu",
                           "children": [],
                           "type": "original",
                           "index": 3120
                          }
                         ],
                         "type": "original",
                         "index": 3118
                        }
                       ],
                       "type": "original",
                       "index": 3117
                      }
                     ],
                     "type": "original",
                     "index": 3116
                    }
                   ],
                   "type": "original",
                   "index": 3115
                  },
                  {
                   "size": 1,
                   "sourcefile": "",
                   "name": "task_work_add",
                   "label": "task_work_add",
                   "children": [
                    {
                     "size": 1,
                     "sourcefile": "",
                     "name": "kick_process",
                     "label": "kick_process",
                     "children": [],
                     "type": "original",
                     "index": 3064
                    }
                   ],
                   "type": "original",
                   "index": 3059
                  }
                 ],
                 "type": "original",
                 "index": 2957
                },
                {
                 "size": 1,
                 "sourcefile": "",
                 "name": "__legitimize_mnt",
                 "label": "__legitimize_mnt",
                 "children": [],
                 "type": "original",
                 "index": 2943
                }
               ],
               "type": "original",
               "index": 2942
              },
              {
               "size": 1,
               "sourcefile": "",
               "name": "drop_links",
               "label": "drop_links",
               "children": [],
               "type": "original",
               "index": 2954
              }
             ],
             "type": "original",
             "index": 2941
            },
            {
             "size": 1,
             "sourcefile": "",
             "name": "dput",
             "label": "dput",
             "children": [
              {
               "size": 1,
               "sourcefile": "",
               "name": "list_lru_add",
               "label": "list_lru_add",
               "children": [],
               "type": "original",
               "index": 3103
              },
              {
               "size": 1,
               "sourcefile": "",
               "name": "__dentry_kill",
               "label": "__dentry_kill",
               "children": [
                {
                 "size": 1,
                 "sourcefile": "",
                 "name": "lockref_mark_dead",
                 "label": "lockref_mark_dead",
                 "children": [],
                 "type": "original",
                 "index": 3031
                },
                {
                 "size": 1,
                 "sourcefile": "",
                 "name": "__fsnotify_inode_delete",
                 "label": "__fsnotify_inode_delete",
                 "children": [
                  {
                   "size": 1,
                   "sourcefile": "",
                   "name": "fsnotify_clear_marks_by_inode",
                   "label": "fsnotify_clear_marks_by_inode",
                   "children": [
                    {
                     "size": 1,
                     "sourcefile": "",
                     "name": "fsnotify_destroy_marks",
                     "label": "fsnotify_destroy_marks",
                     "children": [
                      {
                       "size": 1,
                       "sourcefile": "",
                       "name": "fsnotify_put_group",
                       "label": "fsnotify_put_group",
                       "children": [],
                       "type": "original",
                       "index": 3122
                      }
                     ],
                     "type": "original",
                     "index": 3050
                    }
                   ],
                   "type": "original",
                   "index": 3049
                  }
                 ],
                 "type": "original",
                 "index": 3048
                }
               ],
               "type": "original",
               "index": 3030
              },
              {
               "size": 1,
               "sourcefile": "",
               "name": "lockref_put_return",
               "label": "lockref_put_return",
               "children": [],
               "type": "original",
               "index": 2951
              },
              {
               "size": 1,
               "sourcefile": "",
               "name": "lockref_put_or_lock",
               "label": "lockref_put_or_lock",
               "children": [],
               "type": "original",
               "index": 3058
              }
             ],
             "type": "original",
             "index": 2950
            },
            {
             "size": 1,
             "sourcefile": "",
             "name": "atime_needs_update",
             "label": "atime_needs_update",
             "children": [],
             "type": "original",
             "index": 3087
            },
            {
             "size": 1,
             "sourcefile": "",
             "name": "mntput",
             "label": "mntput",
             "children": [],
             "type": "original",
             "index": 2956
            },
            {
             "size": 1,
             "sourcefile": "",
             "name": "security_inode_follow_link",
             "label": "security_inode_follow_link",
             "children": [],
             "type": "original",
             "index": 3088
            }
           ],
           "type": "original",
           "index": 2932
          },
          {
           "size": 1,
           "sourcefile": "",
           "name": "terminate_walk",
           "label": "terminate_walk",
           "children": [],
           "type": "original",
           "index": 2953
          },
          {
           "size": 1,
           "sourcefile": "",
           "name": "walk_component",
           "label": "walk_component",
           "children": [
            {
             "size": 1,
             "sourcefile": "",
             "name": "pick_link",
             "label": "pick_link",
             "children": [],
             "type": "original",
             "index": 3086
            },
            {
             "size": 1,
             "sourcefile": "",
             "name": "mutex_lock",
             "label": "mutex_lock",
             "children": [
              {
               "size": 1,
               "sourcefile": "",
               "name": "__mutex_lock_slowpath",
               "label": "__mutex_lock_slowpath",
               "children": [
                {
                 "size": 1,
                 "sourcefile": "",
                 "name": "mutex_optimistic_spin",
                 "label": "mutex_optimistic_spin",
                 "children": [],
                 "type": "original",
                 "index": 3092
                },
                {
                 "size": 1,
                 "sourcefile": "",
                 "name": "schedule_preempt_disabled",
                 "label": "schedule_preempt_disabled",
                 "children": [],
                 "type": "original",
                 "index": 3093
                }
               ],
               "type": "original",
               "index": 3091
              }
             ],
             "type": "original",
             "index": 2946
            },
            {
             "size": 1,
             "sourcefile": "",
             "name": "follow_managed",
             "label": "follow_managed",
             "children": [
              {
               "size": 1,
               "sourcefile": "",
               "name": "mntget",
               "label": "mntget",
               "children": [],
               "type": "original",
               "index": 3078
              },
              {
               "size": 1,
               "sourcefile": "",
               "name": "lockref_get",
               "label": "lockref_get",
               "children": [],
               "type": "original",
               "index": 3079
              }
             ],
             "type": "original",
             "index": 2949
            },
            {
             "size": 1,
             "sourcefile": "",
             "name": "mutex_unlock",
             "label": "mutex_unlock",
             "children": [
              {
               "size": 1,
               "sourcefile": "",
               "name": "__mutex_unlock_slowpath",
               "label": "__mutex_unlock_slowpath",
               "children": [],
               "type": "original",
               "index": 3094
              }
             ],
             "type": "original",
             "index": 2947
            },
            {
             "size": 1,
             "sourcefile": "",
             "name": "lookup_fast",
             "label": "lookup_fast",
             "children": [
              {
               "size": 1,
               "sourcefile": "",
               "name": "__d_lookup",
               "label": "__d_lookup",
               "children": [],
               "type": "original",
               "index": 2948
              },
              {
               "size": 1,
               "sourcefile": "",
               "name": "d_invalidate",
               "label": "d_invalidate",
               "children": [
                {
                 "size": 1,
                 "sourcefile": "",
                 "name": "check_and_drop",
                 "label": "check_and_drop",
                 "children": [
                  {
                   "size": 1,
                   "sourcefile": "",
                   "name": "__d_drop",
                   "label": "__d_drop",
                   "children": [],
                   "type": "original",
                   "index": 3032
                  }
                 ],
                 "type": "original",
                 "index": 3027
                },
                {
                 "size": 1,
                 "sourcefile": "",
                 "name": "shrink_dentry_list",
                 "label": "shrink_dentry_list",
                 "children": [
                  {
                   "size": 1,
                   "sourcefile": "",
                   "name": "dentry_free",
                   "label": "dentry_free",
                   "children": [
                    {
                     "size": 1,
                     "sourcefile": "",
                     "name": "__d_free",
                     "label": "__d_free",
                     "children": [],
                     "type": "original",
                     "index": 3109
                    }
                   ],
                   "type": "original",
                   "index": 3057
                  }
                 ],
                 "type": "original",
                 "index": 3028
                },
                {
                 "size": 1,
                 "sourcefile": "",
                 "name": "d_walk",
                 "label": "d_walk",
                 "children": [],
                 "type": "original",
                 "index": 3021
                },
                {
                 "size": 1,
                 "sourcefile": "",
                 "name": "detach_and_collect",
                 "label": "detach_and_collect",
                 "children": [
                  {
                   "size": 1,
                   "sourcefile": "",
                   "name": "select_collect",
                   "label": "select_collect",
                   "children": [
                    {
                     "size": 1,
                     "sourcefile": "",
                     "name": "d_shrink_add",
                     "label": "d_shrink_add",
                     "children": [],
                     "type": "original",
                     "index": 3026
                    },
                    {
                     "size": 1,
                     "sourcefile": "",
                     "name": "d_lru_del",
                     "label": "d_lru_del",
                     "children": [
                      {
                       "size": 1,
                       "sourcefile": "",
                       "name": "list_lru_del",
                       "label": "list_lru_del",
                       "children": [],
                       "type": "original",
                       "index": 3025
                      }
                     ],
                     "type": "original",
                     "index": 3024
                    }
                   ],
                   "type": "original",
                   "index": 3023
                  }
                 ],
                 "type": "original",
                 "index": 3022
                }
               ],
               "type": "original",
               "index": 3020
              },
              {
               "size": 1,
               "sourcefile": "",
               "name": "__d_lookup_rcu",
               "label": "__d_lookup_rcu",
               "children": [],
               "type": "original",
               "index": 2939
              },
              {
               "size": 1,
               "sourcefile": "",
               "name": "__lookup_mnt",
               "label": "__lookup_mnt",
               "children": [],
               "type": "original",
               "index": 2940
              }
             ],
             "type": "original",
             "index": 2938
            },
            {
             "size": 1,
             "sourcefile": "",
             "name": "__lookup_hash",
             "label": "__lookup_hash",
             "children": [
              {
               "size": 1,
               "sourcefile": "",
               "name": "lookup_dcache",
               "label": "lookup_dcache",
               "children": [
                {
                 "size": 1,
                 "sourcefile": "",
                 "name": "d_lookup",
                 "label": "d_lookup",
                 "children": [],
                 "type": "original",
                 "index": 3082
                },
                {
                 "size": 1,
                 "sourcefile": "",
                 "name": "d_alloc",
                 "label": "d_alloc",
                 "children": [
                  {
                   "size": 1,
                   "sourcefile": "",
                   "name": "__d_alloc",
                   "label": "__d_alloc",
                   "children": [
                    {
                     "size": 1,
                     "sourcefile": "",
                     "name": "memcpy",
                     "label": "memcpy",
                     "children": [],
                     "type": "original",
                     "index": 3085
                    },
                    {
                     "size": 1,
                     "sourcefile": "",
                     "name": "__kmalloc",
                     "label": "__kmalloc",
                     "children": [
                      {
                       "size": 1,
                       "sourcefile": "",
                       "name": "kmalloc_slab",
                       "label": "kmalloc_slab",
                       "children": [],
                       "type": "original",
                       "index": 3105
                      }
                     ],
                     "type": "original",
                     "index": 3104
                    },
                    {
                     "size": 1,
                     "sourcefile": "",
                     "name": "d_set_d_op",
                     "label": "d_set_d_op",
                     "children": [],
                     "type": "original",
                     "index": 3089
                    }
                   ],
                   "type": "original",
                   "index": 3084
                  }
                 ],
                 "type": "original",
                 "index": 3083
                }
               ],
               "type": "original",
               "index": 3081
              },
              {
               "size": 1,
               "sourcefile": "",
               "name": "lookup_real",
               "label": "lookup_real",
               "children": [],
               "type": "original",
               "index": 3090
              }
             ],
             "type": "original",
             "index": 3080
            }
           ],
           "type": "original",
           "index": 2937
          },
          {
           "size": 1,
           "sourcefile": "",
           "name": "path_init",
           "label": "path_init",
           "children": [
            {
             "size": 1,
             "sourcefile": "",
             "name": "set_root_rcu",
             "label": "set_root_rcu",
             "children": [],
             "type": "original",
             "index": 2931
            },
            {
             "size": 1,
             "sourcefile": "",
             "name": "path_get",
             "label": "path_get",
             "children": [],
             "type": "original",
             "index": 3077
            },
            {
             "size": 1,
             "sourcefile": "",
             "name": "__fdget_raw",
             "label": "__fdget_raw",
             "children": [],
             "type": "original",
             "index": 3102
            },
            {
             "size": 1,
             "sourcefile": "",
             "name": "inode_permission",
             "label": "inode_permission",
             "children": [
              {
               "size": 1,
               "sourcefile": "",
               "name": "__inode_permission",
               "label": "__inode_permission",
               "children": [
                {
                 "size": 1,
                 "sourcefile": "",
                 "name": "generic_permission",
                 "label": "generic_permission",
                 "children": [
                  {
                   "size": 1,
                   "sourcefile": "",
                   "name": "kfree_call_rcu",
                   "label": "kfree_call_rcu",
                   "children": [],
                   "type": "original",
                   "index": 3121
                  }
                 ],
                 "type": "original",
                 "index": 2935
                },
                {
                 "size": 1,
                 "sourcefile": "",
                 "name": "security_inode_permission",
                 "label": "security_inode_permission",
                 "children": [],
                 "type": "original",
                 "index": 2936
                }
               ],
               "type": "original",
               "index": 2934
              }
             ],
             "type": "original",
             "index": 2933
            }
           ],
           "type": "original",
           "index": 2930
          },
          {
           "size": 1,
           "sourcefile": "",
           "name": "complete_walk",
           "label": "complete_walk",
           "children": [],
           "type": "original",
           "index": 2952
          }
         ],
         "type": "original",
         "index": 2929
        },
        {
         "size": 1,
         "sourcefile": "",
         "name": "restore_nameidata",
         "label": "restore_nameidata",
         "children": [],
         "type": "original",
         "index": 2958
        }
       ],
       "type": "original",
       "index": 2928
      },
      {
       "size": 1,
       "sourcefile": "",
       "name": "getname_flags",
       "label": "getname_flags",
       "children": [
        {
         "size": 1,
         "sourcefile": "",
         "name": "kmem_cache_alloc_trace",
         "label": "kmem_cache_alloc_trace",
         "children": [],
         "type": "original",
         "index": 2975
        },
        {
         "size": 1,
         "sourcefile": "",
         "name": "kmem_cache_alloc",
         "label": "kmem_cache_alloc",
         "children": [
          {
           "size": 1,
           "sourcefile": "",
           "name": "__slab_alloc",
           "label": "__slab_alloc",
           "children": [
            {
             "size": 1,
             "sourcefile": "",
             "name": "__cmpxchg_double_slab",
             "label": "__cmpxchg_double_slab",
             "children": [],
             "type": "original",
             "index": 2999
            },
            {
             "size": 1,
             "sourcefile": "",
             "name": "next_zones_zonelist",
             "label": "next_zones_zonelist",
             "children": [],
             "type": "original",
             "index": 3072
            },
            {
             "size": 1,
             "sourcefile": "",
             "name": "__cpuset_node_allowed",
             "label": "__cpuset_node_allowed",
             "children": [],
             "type": "original",
             "index": 3073
            }
           ],
           "type": "original",
           "index": 2998
          },
          {
           "size": 1,
           "sourcefile": "",
           "name": "_cond_resched",
           "label": "_cond_resched",
           "children": [
            {
             "size": 1,
             "sourcefile": "",
             "name": "preempt_schedule_common",
             "label": "preempt_schedule_common",
             "children": [
              {
               "size": 1,
               "sourcefile": "",
               "name": "__schedule",
               "label": "__schedule",
               "children": [
                {
                 "size": 1,
                 "sourcefile": "",
                 "name": "finish_task_switch",
                 "label": "finish_task_switch",
                 "children": [
                  {
                   "size": 1,
                   "sourcefile": "",
                   "name": "kprobe_flush_task",
                   "label": "kprobe_flush_task",
                   "children": [],
                   "type": "original",
                   "index": 3018
                  },
                  {
                   "size": 1,
                   "sourcefile": "",
                   "name": "__perf_event_task_sched_in",
                   "label": "__perf_event_task_sched_in",
                   "children": [
                    {
                     "size": 1,
                     "sourcefile": "",
                     "name": "perf_event_context_sched_in",
                     "label": "perf_event_context_sched_in",
                     "children": [
                      {
                       "size": 1,
                       "sourcefile": "",
                       "name": "perf_event_sched_in",
                       "label": "perf_event_sched_in",
                       "children": [
                        {
                         "size": 1,
                         "sourcefile": "",
                         "name": "ctx_sched_in",
                         "label": "ctx_sched_in",
                         "children": [
                          {
                           "size": 1,
                           "sourcefile": "",
                           "name": "update_group_times",
                           "label": "update_group_times",
                           "children": [],
                           "type": "original",
                           "index": 3003
                          },
                          {
                           "size": 1,
                           "sourcefile": "",
                           "name": "group_sched_in",
                           "label": "group_sched_in",
                           "children": [
                            {
                             "size": 1,
                             "sourcefile": "",
                             "name": "event_sched_in",
                             "label": "event_sched_in",
                             "children": [],
                             "type": "original",
                             "index": 2916
                            }
                           ],
                           "type": "original",
                           "index": 2915
                          }
                         ],
                         "type": "original",
                         "index": 2914
                        }
                       ],
                       "type": "original",
                       "index": 2913
                      },
                      {
                       "size": 1,
                       "sourcefile": "",
                       "name": "perf_ctx_unlock",
                       "label": "perf_ctx_unlock",
                       "children": [],
                       "type": "original",
                       "index": 2918
                      }
                     ],
                     "type": "original",
                     "index": 2912
                    }
                   ],
                   "type": "original",
                   "index": 2911
                  },
                  {
                   "size": 1,
                   "sourcefile": "",
                   "name": "__mmdrop",
                   "label": "__mmdrop",
                   "children": [
                    {
                     "size": 1,
                     "sourcefile": "",
                     "name": "pgd_free",
                     "label": "pgd_free",
                     "children": [
                      {
                       "size": 1,
                       "sourcefile": "",
                       "name": "free_pages",
                       "label": "free_pages",
                       "children": [
                        {
                         "size": 1,
                         "sourcefile": "",
                         "name": "__free_pages",
                         "label": "__free_pages",
                         "children": [
                          {
                           "size": 1,
                           "sourcefile": "",
                           "name": "__free_pages_ok",
                           "label": "__free_pages_ok",
                           "children": [],
                           "type": "original",
                           "index": 3123
                          },
                          {
                           "size": 1,
                           "sourcefile": "",
                           "name": "free_hot_cold_page",
                           "label": "free_hot_cold_page",
                           "children": [
                            {
                             "size": 1,
                             "sourcefile": "",
                             "name": "get_pfnblock_flags_mask",
                             "label": "get_pfnblock_flags_mask",
                             "children": [],
                             "type": "original",
                             "index": 3015
                            },
                            {
                             "size": 1,
                             "sourcefile": "",
                             "name": "free_pages_prepare",
                             "label": "free_pages_prepare",
                             "children": [],
                             "type": "original",
                             "index": 3014
                            },
                            {
                             "size": 1,
                             "sourcefile": "",
                             "name": "free_one_page",
                             "label": "free_one_page",
                             "children": [
                              {
                               "size": 1,
                               "sourcefile": "",
                               "name": "__mod_zone_page_state",
                               "label": "__mod_zone_page_state",
                               "children": [],
                               "type": "original",
                               "index": 3125
                              }
                             ],
                             "type": "original",
                             "index": 3124
                            },
                            {
                             "size": 1,
                             "sourcefile": "",
                             "name": "free_pcppages_bulk",
                             "label": "free_pcppages_bulk",
                             "children": [],
                             "type": "original",
                             "index": 3131
                            }
                           ],
                           "type": "original",
                           "index": 3013
                          }
                         ],
                         "type": "original",
                         "index": 3012
                        }
                       ],
                       "type": "original",
                       "index": 3011
                      }
                     ],
                     "type": "original",
                     "index": 3010
                    },
                    {
                     "size": 1,
                     "sourcefile": "",
                     "name": "destroy_context",
                     "label": "destroy_context",
                     "children": [
                      {
                       "size": 1,
                       "sourcefile": "",
                       "name": "free_ldt_struct",
                       "label": "free_ldt_struct",
                       "children": [],
                       "type": "original",
                       "index": 3017
                      }
                     ],
                     "type": "original",
                     "index": 3016
                    }
                   ],
                   "type": "original",
                   "index": 3009
                  }
                 ],
                 "type": "original",
                 "index": 2910
                },
                {
                 "size": 1,
                 "sourcefile": "",
                 "name": "_raw_spin_lock",
                 "label": "_raw_spin_lock",
                 "children": [],
                 "type": "original",
                 "index": 2894
                },
                {
                 "size": 1,
                 "sourcefile": "",
                 "name": "wq_worker_waking_up",
                 "label": "wq_worker_waking_up",
                 "children": [
                  {
                   "size": 1,
                   "sourcefile": "",
                   "name": "kthread_data",
                   "label": "kthread_data",
                   "children": [],
                   "type": "original",
                   "index": 2922
                  }
                 ],
                 "type": "original",
                 "index": 2921
                },
                {
                 "size": 1,
                 "sourcefile": "",
                 "name": "update_rq_clock",
                 "label": "update_rq_clock",
                 "children": [
                  {
                   "size": 1,
                   "sourcefile": "",
                   "name": "sched_clock_cpu",
                   "label": "sched_clock_cpu",
                   "children": [
                    {
                     "size": 1,
                     "sourcefile": "",
                     "name": "sched_clock",
                     "label": "sched_clock",
                     "children": [],
                     "type": "original",
                     "index": 2897
                    }
                   ],
                   "type": "original",
                   "index": 2896
                  }
                 ],
                 "type": "original",
                 "index": 2895
                },
                {
                 "size": 1,
                 "sourcefile": "",
                 "name": "__perf_event_task_sched_out",
                 "label": "__perf_event_task_sched_out",
                 "children": [
                  {
                   "size": 1,
                   "sourcefile": "",
                   "name": "update_event_times",
                   "label": "update_event_times",
                   "children": [],
                   "type": "original",
                   "index": 3004
                  },
                  {
                   "size": 1,
                   "sourcefile": "",
                   "name": "perf_cgroup_switch",
                   "label": "perf_cgroup_switch",
                   "children": [],
                   "type": "original",
                   "index": 3005
                  },
                  {
                   "size": 1,
                   "sourcefile": "",
                   "name": "perf_event_update_userpage",
                   "label": "perf_event_update_userpage",
                   "children": [],
                   "type": "original",
                   "index": 2917
                  },
                  {
                   "size": 1,
                   "sourcefile": "",
                   "name": "ctx_sched_out",
                   "label": "ctx_sched_out",
                   "children": [
                    {
                     "size": 1,
                     "sourcefile": "",
                     "name": "perf_pmu_disable",
                     "label": "perf_pmu_disable",
                     "children": [],
                     "type": "original",
                     "index": 2905
                    },
                    {
                     "size": 1,
                     "sourcefile": "",
                     "name": "perf_pmu_enable",
                     "label": "perf_pmu_enable",
                     "children": [],
                     "type": "original",
                     "index": 2908
                    },
                    {
                     "size": 1,
                     "sourcefile": "",
                     "name": "group_sched_out",
                     "label": "group_sched_out",
                     "children": [
                      {
                       "size": 1,
                       "sourcefile": "",
                       "name": "event_sched_out",
                       "label": "event_sched_out",
                       "children": [],
                       "type": "original",
                       "index": 2907
                      }
                     ],
                     "type": "original",
                     "index": 2906
                    }
                   ],
                   "type": "original",
                   "index": 2903
                  },
                  {
                   "size": 1,
                   "sourcefile": "",
                   "name": "local_clock",
                   "label": "local_clock",
                   "children": [],
                   "type": "original",
                   "index": 2904
                  }
                 ],
                 "type": "original",
                 "index": 2902
                },
                {
                 "size": 1,
                 "sourcefile": "",
                 "name": "_raw_spin_lock_irq",
                 "label": "_raw_spin_lock_irq",
                 "children": [],
                 "type": "original",
                 "index": 2899
                },
                {
                 "size": 1,
                 "sourcefile": "",
                 "name": "___perf_sw_event",
                 "label": "___perf_sw_event",
                 "children": [
                  {
                   "size": 1,
                   "sourcefile": "",
                   "name": "perf_exclude_event",
                   "label": "perf_exclude_event",
                   "children": [],
                   "type": "original",
                   "index": 3019
                  }
                 ],
                 "type": "original",
                 "index": 2901
                },
                {
                 "size": 1,
                 "sourcefile": "",
                 "name": "rcu_note_context_switch",
                 "label": "rcu_note_context_switch",
                 "children": [],
                 "type": "original",
                 "index": 2900
                },
                {
                 "size": 1,
                 "sourcefile": "",
                 "name": "ttwu_do_wakeup",
                 "label": "ttwu_do_wakeup",
                 "children": [
                  {
                   "size": 1,
                   "sourcefile": "",
                   "name": "check_preempt_curr",
                   "label": "check_preempt_curr",
                   "children": [
                    {
                     "size": 1,
                     "sourcefile": "",
                     "name": "resched_curr",
                     "label": "resched_curr",
                     "children": [],
                     "type": "original",
                     "index": 2925
                    }
                   ],
                   "type": "original",
                   "index": 2924
                  }
                 ],
                 "type": "original",
                 "index": 2923
                },
                {
                 "size": 1,
                 "sourcefile": "",
                 "name": "deactivate_task",
                 "label": "deactivate_task",
                 "children": [
                  {
                   "size": 1,
                   "sourcefile": "",
                   "name": "dequeue_task",
                   "label": "dequeue_task",
                   "children": [],
                   "type": "original",
                   "index": 3008
                  }
                 ],
                 "type": "original",
                 "index": 3007
                },
                {
                 "size": 1,
                 "sourcefile": "",
                 "name": "_raw_spin_trylock",
                 "label": "_raw_spin_trylock",
                 "children": [],
                 "type": "original",
                 "index": 3029
                },
                {
                 "size": 1,
                 "sourcefile": "",
                 "name": "__switch_to",
                 "label": "__switch_to",
                 "children": [],
                 "type": "original",
                 "index": 2909
                },
                {
                 "size": 1,
                 "sourcefile": "",
                 "name": "activate_task",
                 "label": "activate_task",
                 "children": [
                  {
                   "size": 1,
                   "sourcefile": "",
                   "name": "enqueue_task",
                   "label": "enqueue_task",
                   "children": [],
                   "type": "original",
                   "index": 2920
                  }
                 ],
                 "type": "original",
                 "index": 2919
                },
                {
                 "size": 1,
                 "sourcefile": "",
                 "name": "ttwu_stat",
                 "label": "ttwu_stat",
                 "children": [],
                 "type": "original",
                 "index": 2926
                },
                {
                 "size": 1,
                 "sourcefile": "",
                 "name": "hrtimer_active",
                 "label": "hrtimer_active",
                 "children": [],
                 "type": "original",
                 "index": 2898
                },
                {
                 "size": 1,
                 "sourcefile": "",
                 "name": "hrtimer_cancel",
                 "label": "hrtimer_cancel",
                 "children": [
                  {
                   "size": 1,
                   "sourcefile": "",
                   "name": "hrtimer_try_to_cancel",
                   "label": "hrtimer_try_to_cancel",
                   "children": [
                    {
                     "size": 1,
                     "sourcefile": "",
                     "name": "__remove_hrtimer",
                     "label": "__remove_hrtimer",
                     "children": [
                      {
                       "size": 1,
                       "sourcefile": "",
                       "name": "__hrtimer_get_next_event",
                       "label": "__hrtimer_get_next_event",
                       "children": [],
                       "type": "original",
                       "index": 2990
                      },
                      {
                       "size": 1,
                       "sourcefile": "",
                       "name": "tick_program_event",
                       "label": "tick_program_event",
                       "children": [
                        {
                         "size": 1,
                         "sourcefile": "",
                         "name": "clockevents_program_event",
                         "label": "clockevents_program_event",
                         "children": [
                          {
                           "size": 1,
                           "sourcefile": "",
                           "name": "ktime_get",
                           "label": "ktime_get",
                           "children": [],
                           "type": "original",
                           "index": 2993
                          }
                         ],
                         "type": "original",
                         "index": 2992
                        }
                       ],
                       "type": "original",
                       "index": 2991
                      },
                      {
                       "size": 1,
                       "sourcefile": "",
                       "name": "timerqueue_del",
                       "label": "timerqueue_del",
                       "children": [
                        {
                         "size": 1,
                         "sourcefile": "",
                         "name": "rb_erase",
                         "label": "rb_erase",
                         "children": [],
                         "type": "original",
                         "index": 2989
                        },
                        {
                         "size": 1,
                         "sourcefile": "",
                         "name": "rb_next",
                         "label": "rb_next",
                         "children": [],
                         "type": "original",
                         "index": 2988
                        }
                       ],
                       "type": "original",
                       "index": 2987
                      }
                     ],
                     "type": "original",
                     "index": 2986
                    }
                   ],
                   "type": "original",
                   "index": 2985
                  }
                 ],
                 "type": "original",
                 "index": 2984
                }
               ],
               "type": "original",
               "index": 2893
              }
             ],
             "type": "original",
             "index": 2892
            }
           ],
           "type": "original",
           "index": 2891
          },
          {
           "size": 1,
           "sourcefile": "",
           "name": "memset",
           "label": "memset",
           "children": [],
           "type": "original",
           "index": 2976
          }
         ],
         "type": "original",
         "index": 2890
        },
        {
         "size": 1,
         "sourcefile": "",
         "name": "strncpy_from_user",
         "label": "strncpy_from_user",
         "children": [],
         "type": "original",
         "index": 2927
        },
        {
         "size": 1,
         "sourcefile": "",
         "name": "kfree",
         "label": "kfree",
         "children": [],
         "type": "original",
         "index": 3000
        },
        {
         "size": 1,
         "sourcefile": "",
         "name": "kmem_cache_free",
         "label": "kmem_cache_free",
         "children": [
          {
           "size": 1,
           "sourcefile": "",
           "name": "__slab_free",
           "label": "__slab_free",
           "children": [
            {
             "size": 1,
             "sourcefile": "",
             "name": "cmpxchg_double_slab",
             "label": "cmpxchg_double_slab",
             "children": [],
             "type": "original",
             "index": 2995
            },
            {
             "size": 1,
             "sourcefile": "",
             "name": "put_cpu_partial",
             "label": "put_cpu_partial",
             "children": [
              {
               "size": 1,
               "sourcefile": "",
               "name": "unfreeze_partials",
               "label": "unfreeze_partials",
               "children": [],
               "type": "original",
               "index": 3111
              }
             ],
             "type": "original",
             "index": 2996
            },
            {
             "size": 1,
             "sourcefile": "",
             "name": "discard_slab",
             "label": "discard_slab",
             "children": [
              {
               "size": 1,
               "sourcefile": "",
               "name": "__free_slab",
               "label": "__free_slab",
               "children": [
                {
                 "size": 1,
                 "sourcefile": "",
                 "name": "mod_zone_page_state",
                 "label": "mod_zone_page_state",
                 "children": [],
                 "type": "original",
                 "index": 3114
                }
               ],
               "type": "original",
               "index": 3113
              }
             ],
             "type": "original",
             "index": 3112
            }
           ],
           "type": "original",
           "index": 2994
          }
         ],
         "type": "original",
         "index": 2960
        },
        {
         "size": 1,
         "sourcefile": "",
         "name": "putname",
         "label": "putname",
         "children": [],
         "type": "original",
         "index": 2959
        }
       ],
       "type": "original",
       "index": 2889
      }
     ],
     "type": "original",
     "index": 2888
    },
    {
     "size": 1,
     "sourcefile": "",
     "name": "path_put",
     "label": "path_put",
     "children": [],
     "type": "original",
     "index": 2955
    },
    {
     "size": 1,
     "sourcefile": "",
     "name": "fput",
     "label": "fput",
     "children": [
      {
       "size": 1,
       "sourcefile": "",
       "name": "____fput",
       "label": "____fput",
       "children": [
        {
         "size": 1,
         "sourcefile": "",
         "name": "__fput",
         "label": "__fput",
         "children": [
          {
           "size": 1,
           "sourcefile": "",
           "name": "cdev_put",
           "label": "cdev_put",
           "children": [
            {
             "size": 1,
             "sourcefile": "",
             "name": "kobject_put",
             "label": "kobject_put",
             "children": [],
             "type": "original",
             "index": 3133
            }
           ],
           "type": "original",
           "index": 3132
          },
          {
           "size": 1,
           "sourcefile": "",
           "name": "__mnt_drop_write",
           "label": "__mnt_drop_write",
           "children": [],
           "type": "original",
           "index": 3097
          },
          {
           "size": 1,
           "sourcefile": "",
           "name": "ima_file_free",
           "label": "ima_file_free",
           "children": [],
           "type": "original",
           "index": 3068
          },
          {
           "size": 1,
           "sourcefile": "",
           "name": "locks_remove_file",
           "label": "locks_remove_file",
           "children": [
            {
             "size": 1,
             "sourcefile": "",
             "name": "locks_remove_posix",
             "label": "locks_remove_posix",
             "children": [],
             "type": "original",
             "index": 3099
            }
           ],
           "type": "original",
           "index": 3067
          },
          {
           "size": 1,
           "sourcefile": "",
           "name": "security_file_free",
           "label": "security_file_free",
           "children": [],
           "type": "original",
           "index": 3069
          },
          {
           "size": 1,
           "sourcefile": "",
           "name": "module_put",
           "label": "module_put",
           "children": [],
           "type": "original",
           "index": 3070
          },
          {
           "size": 1,
           "sourcefile": "",
           "name": "put_pid",
           "label": "put_pid",
           "children": [
            {
             "size": 1,
             "sourcefile": "",
             "name": "put_pid_ns",
             "label": "put_pid_ns",
             "children": [],
             "type": "original",
             "index": 3110
            }
           ],
           "type": "original",
           "index": 3071
          }
         ],
         "type": "original",
         "index": 3066
        }
       ],
       "type": "original",
       "index": 3065
      }
     ],
     "type": "original",
     "index": 2997
    },
    {
     "size": 1,
     "sourcefile": "",
     "name": "utimes_common",
     "label": "utimes_common",
     "children": [
      {
       "size": 1,
       "sourcefile": "",
       "name": "mnt_want_write",
       "label": "mnt_want_write",
       "children": [
        {
         "size": 1,
         "sourcefile": "",
         "name": "__sb_start_write",
         "label": "__sb_start_write",
         "children": [
          {
           "size": 1,
           "sourcefile": "",
           "name": "__percpu_counter_add",
           "label": "__percpu_counter_add",
           "children": [
            {
             "size": 1,
             "sourcefile": "",
             "name": "_raw_spin_lock_irqsave",
             "label": "_raw_spin_lock_irqsave",
             "children": [],
             "type": "original",
             "index": 2965
            },
            {
             "size": 1,
             "sourcefile": "",
             "name": "_raw_spin_unlock_irqrestore",
             "label": "_raw_spin_unlock_irqrestore",
             "children": [],
             "type": "original",
             "index": 2966
            }
           ],
           "type": "original",
           "index": 2964
          },
          {
           "size": 1,
           "sourcefile": "",
           "name": "schedule",
           "label": "schedule",
           "children": [],
           "type": "original",
           "index": 3006
          },
          {
           "size": 1,
           "sourcefile": "",
           "name": "finish_wait",
           "label": "finish_wait",
           "children": [],
           "type": "original",
           "index": 3108
          }
         ],
         "type": "original",
         "index": 2963
        },
        {
         "size": 1,
         "sourcefile": "",
         "name": "__sb_end_write",
         "label": "__sb_end_write",
         "children": [
          {
           "size": 1,
           "sourcefile": "",
           "name": "__wake_up",
           "label": "__wake_up",
           "children": [
            {
             "size": 1,
             "sourcefile": "",
             "name": "__wake_up_common",
             "label": "__wake_up_common",
             "children": [],
             "type": "original",
             "index": 3002
            }
           ],
           "type": "original",
           "index": 3001
          }
         ],
         "type": "original",
         "index": 2982
        },
        {
         "size": 1,
         "sourcefile": "",
         "name": "__mnt_want_write",
         "label": "__mnt_want_write",
         "children": [
          {
           "size": 1,
           "sourcefile": "",
           "name": "__mnt_is_readonly",
           "label": "__mnt_is_readonly",
           "children": [],
           "type": "original",
           "index": 2968
          }
         ],
         "type": "original",
         "index": 2967
        }
       ],
       "type": "original",
       "index": 2962
      },
      {
       "size": 1,
       "sourcefile": "",
       "name": "mnt_drop_write",
       "label": "mnt_drop_write",
       "children": [],
       "type": "original",
       "index": 2981
      },
      {
       "size": 1,
       "sourcefile": "",
       "name": "inode_owner_or_capable",
       "label": "inode_owner_or_capable",
       "children": [
        {
         "size": 1,
         "sourcefile": "",
         "name": "from_kuid",
         "label": "from_kuid",
         "children": [],
         "type": "original",
         "index": 2983
        }
       ],
       "type": "original",
       "index": 2974
      },
      {
       "size": 1,
       "sourcefile": "",
       "name": "iput",
       "label": "iput",
       "children": [
        {
         "size": 1,
         "sourcefile": "",
         "name": "__mark_inode_dirty",
         "label": "__mark_inode_dirty",
         "children": [
          {
           "size": 1,
           "sourcefile": "",
           "name": "__inode_attach_wb",
           "label": "__inode_attach_wb",
           "children": [],
           "type": "original",
           "index": 3101
          }
         ],
         "type": "original",
         "index": 3100
        },
        {
         "size": 1,
         "sourcefile": "",
         "name": "_atomic_dec_and_lock",
         "label": "_atomic_dec_and_lock",
         "children": [],
         "type": "original",
         "index": 3034
        },
        {
         "size": 1,
         "sourcefile": "",
         "name": "evict",
         "label": "evict",
         "children": [
          {
           "size": 1,
           "sourcefile": "",
           "name": "wake_up_bit",
           "label": "wake_up_bit",
           "children": [
            {
             "size": 1,
             "sourcefile": "",
             "name": "__wake_up_bit",
             "label": "__wake_up_bit",
             "children": [],
             "type": "original",
             "index": 3042
            }
           ],
           "type": "original",
           "index": 3041
          },
          {
           "size": 1,
           "sourcefile": "",
           "name": "clear_inode",
           "label": "clear_inode",
           "children": [],
           "type": "original",
           "index": 3040
          },
          {
           "size": 1,
           "sourcefile": "",
           "name": "destroy_inode",
           "label": "destroy_inode",
           "children": [
            {
             "size": 1,
             "sourcefile": "",
             "name": "__destroy_inode",
             "label": "__destroy_inode",
             "children": [
              {
               "size": 1,
               "sourcefile": "",
               "name": "security_inode_free",
               "label": "security_inode_free",
               "children": [
                {
                 "size": 1,
                 "sourcefile": "",
                 "name": "integrity_inode_free",
                 "label": "integrity_inode_free",
                 "children": [],
                 "type": "original",
                 "index": 3047
                }
               ],
               "type": "original",
               "index": 3046
              },
              {
               "size": 1,
               "sourcefile": "",
               "name": "inode_has_buffers",
               "label": "inode_has_buffers",
               "children": [],
               "type": "original",
               "index": 3045
              },
              {
               "size": 1,
               "sourcefile": "",
               "name": "locks_free_lock_context",
               "label": "locks_free_lock_context",
               "children": [],
               "type": "original",
               "index": 3051
              }
             ],
             "type": "original",
             "index": 3044
            },
            {
             "size": 1,
             "sourcefile": "",
             "name": "call_rcu_sched",
             "label": "call_rcu_sched",
             "children": [
              {
               "size": 1,
               "sourcefile": "",
               "name": "__call_rcu",
               "label": "__call_rcu",
               "children": [
                {
                 "size": 1,
                 "sourcefile": "",
                 "name": "__call_rcu_nocb_enqueue",
                 "label": "__call_rcu_nocb_enqueue",
                 "children": [
                  {
                   "size": 1,
                   "sourcefile": "",
                   "name": "wake_nocb_leader",
                   "label": "wake_nocb_leader",
                   "children": [],
                   "type": "original",
                   "index": 3056
                  }
                 ],
                 "type": "original",
                 "index": 3055
                },
                {
                 "size": 1,
                 "sourcefile": "",
                 "name": "raise_softirq",
                 "label": "raise_softirq",
                 "children": [
                  {
                   "size": 1,
                   "sourcefile": "",
                   "name": "wake_up_process",
                   "label": "wake_up_process",
                   "children": [
                    {
                     "size": 1,
                     "sourcefile": "",
                     "name": "try_to_wake_up",
                     "label": "try_to_wake_up",
                     "children": [
                      {
                       "size": 1,
                       "sourcefile": "",
                       "name": "ttwu_do_activate",
                       "label": "ttwu_do_activate",
                       "children": [],
                       "type": "original",
                       "index": 3063
                      },
                      {
                       "size": 1,
                       "sourcefile": "",
                       "name": "set_task_cpu",
                       "label": "set_task_cpu",
                       "children": [],
                       "type": "original",
                       "index": 3074
                      }
                     ],
                     "type": "original",
                     "index": 3062
                    }
                   ],
                   "type": "original",
                   "index": 3061
                  }
                 ],
                 "type": "original",
                 "index": 3054
                },
                {
                 "size": 1,
                 "sourcefile": "",
                 "name": "note_gp_changes",
                 "label": "note_gp_changes",
                 "children": [],
                 "type": "original",
                 "index": 3060
                }
               ],
               "type": "original",
               "index": 3053
              }
             ],
             "type": "original",
             "index": 3052
            }
           ],
           "type": "original",
           "index": 3043
          },
          {
           "size": 1,
           "sourcefile": "",
           "name": "inode_wait_for_writeback",
           "label": "inode_wait_for_writeback",
           "children": [
            {
             "size": 1,
             "sourcefile": "",
             "name": "__inode_wait_for_writeback",
             "label": "__inode_wait_for_writeback",
             "children": [
              {
               "size": 1,
               "sourcefile": "",
               "name": "bit_waitqueue",
               "label": "bit_waitqueue",
               "children": [],
               "type": "original",
               "index": 3038
              },
              {
               "size": 1,
               "sourcefile": "",
               "name": "__wait_on_bit",
               "label": "__wait_on_bit",
               "children": [
                {
                 "size": 1,
                 "sourcefile": "",
                 "name": "prepare_to_wait",
                 "label": "prepare_to_wait",
                 "children": [],
                 "type": "original",
                 "index": 3107
                }
               ],
               "type": "original",
               "index": 3106
              }
             ],
             "type": "original",
             "index": 3037
            }
           ],
           "type": "original",
           "index": 3036
          },
          {
           "size": 1,
           "sourcefile": "",
           "name": "truncate_inode_pages_final",
           "label": "truncate_inode_pages_final",
           "children": [],
           "type": "original",
           "index": 3039
          }
         ],
         "type": "original",
         "index": 3035
        }
       ],
       "type": "original",
       "index": 3033
      },
      {
       "size": 1,
       "sourcefile": "",
       "name": "notify_change",
       "label": "notify_change",
       "children": [
        {
         "size": 1,
         "sourcefile": "",
         "name": "current_fs_time",
         "label": "current_fs_time",
         "children": [
          {
           "size": 1,
           "sourcefile": "",
           "name": "current_kernel_time",
           "label": "current_kernel_time",
           "children": [],
           "type": "original",
           "index": 2971
          }
         ],
         "type": "original",
         "index": 2970
        },
        {
         "size": 1,
         "sourcefile": "",
         "name": "evm_inode_post_setattr",
         "label": "evm_inode_post_setattr",
         "children": [],
         "type": "original",
         "index": 2980
        },
        {
         "size": 1,
         "sourcefile": "",
         "name": "fsnotify",
         "label": "fsnotify",
         "children": [
          {
           "size": 1,
           "sourcefile": "",
           "name": "__srcu_read_unlock",
           "label": "__srcu_read_unlock",
           "children": [],
           "type": "original",
           "index": 3076
          },
          {
           "size": 1,
           "sourcefile": "",
           "name": "__srcu_read_lock",
           "label": "__srcu_read_lock",
           "children": [],
           "type": "original",
           "index": 3075
          }
         ],
         "type": "original",
         "index": 2978
        },
        {
         "size": 1,
         "sourcefile": "",
         "name": "security_inode_setattr",
         "label": "security_inode_setattr",
         "children": [
          {
           "size": 1,
           "sourcefile": "",
           "name": "evm_inode_setattr",
           "label": "evm_inode_setattr",
           "children": [],
           "type": "original",
           "index": 2973
          }
         ],
         "type": "original",
         "index": 2972
        },
        {
         "size": 1,
         "sourcefile": "",
         "name": "__fsnotify_parent",
         "label": "__fsnotify_parent",
         "children": [],
         "type": "original",
         "index": 2977
        },
        {
         "size": 1,
         "sourcefile": "",
         "name": "security_inode_need_killpriv",
         "label": "security_inode_need_killpriv",
         "children": [],
         "type": "original",
         "index": 3098
        },
        {
         "size": 1,
         "sourcefile": "",
         "name": "ima_inode_post_setattr",
         "label": "ima_inode_post_setattr",
         "children": [],
         "type": "original",
         "index": 2979
        }
       ],
       "type": "original",
       "index": 2969
      }
     ],
     "type": "original",
     "index": 2961
    },
    {
     "size": 1,
     "sourcefile": "",
     "name": "__fdget",
     "label": "__fdget",
     "children": [
      {
       "size": 1,
       "sourcefile": "",
       "name": "__fget_light",
       "label": "__fget_light",
       "children": [],
       "type": "original",
       "index": 3096
      }
     ],
     "type": "original",
     "index": 3095
    }
   ],
   "type": "original",
   "index": 2887
  }
 ],
 "type": "original",
 "index": 2885
}