{
 "type": "original",
 "index": 2696,
 "children": [
  {
   "type": "original",
   "index": 2749,
   "children": [
    {
     "type": "original",
     "index": 2754,
     "children": [
      {
       "type": "original",
       "index": 2755,
       "children": [
        {
         "type": "original",
         "index": 2756,
         "children": [],
         "label": "__fsnotify_parent",
         "size": 1,
         "sourcefile": "",
         "name": "__fsnotify_parent"
        },
        {
         "type": "original",
         "index": 2759,
         "children": [
          {
           "type": "original",
           "index": 2796,
           "children": [],
           "label": "mutex_lock",
           "size": 1,
           "sourcefile": "",
           "name": "mutex_lock"
          },
          {
           "type": "original",
           "index": 2798,
           "children": [],
           "label": "mutex_unlock",
           "size": 1,
           "sourcefile": "",
           "name": "mutex_unlock"
          }
         ],
         "label": "ima_file_free",
         "size": 1,
         "sourcefile": "",
         "name": "ima_file_free"
        },
        {
         "type": "original",
         "index": 2760,
         "children": [],
         "label": "security_file_free",
         "size": 1,
         "sourcefile": "",
         "name": "security_file_free"
        },
        {
         "type": "original",
         "index": 2764,
         "children": [
          {
           "type": "original",
           "index": 2765,
           "children": [
            {
             "type": "original",
             "index": 2767,
             "children": [
              {
               "type": "original",
               "index": 2768,
               "children": [
                {
                 "type": "original",
                 "index": 2769,
                 "children": [
                  {
                   "type": "original",
                   "index": 2770,
                   "children": [],
                   "label": "__wake_up_common",
                   "size": 1,
                   "sourcefile": "",
                   "name": "__wake_up_common"
                  }
                 ],
                 "label": "__wake_up",
                 "size": 1,
                 "sourcefile": "",
                 "name": "__wake_up"
                }
               ],
               "label": "wake_nocb_leader",
               "size": 1,
               "sourcefile": "",
               "name": "wake_nocb_leader"
              }
             ],
             "label": "__call_rcu_nocb_enqueue",
             "size": 1,
             "sourcefile": "",
             "name": "__call_rcu_nocb_enqueue"
            },
            {
             "type": "original",
             "index": 2766,
             "children": [
              {
               "type": "original",
               "index": 2828,
               "children": [
                {
                 "type": "original",
                 "index": 2829,
                 "children": [
                  {
                   "type": "original",
                   "index": 2830,
                   "children": [],
                   "label": "ttwu_do_activate",
                   "size": 1,
                   "sourcefile": "",
                   "name": "ttwu_do_activate"
                  },
                  {
                   "type": "original",
                   "index": 2834,
                   "children": [],
                   "label": "set_task_cpu",
                   "size": 1,
                   "sourcefile": "",
                   "name": "set_task_cpu"
                  }
                 ],
                 "label": "try_to_wake_up",
                 "size": 1,
                 "sourcefile": "",
                 "name": "try_to_wake_up"
                }
               ],
               "label": "wake_up_process",
               "size": 1,
               "sourcefile": "",
               "name": "wake_up_process"
              }
             ],
             "label": "raise_softirq",
             "size": 1,
             "sourcefile": "",
             "name": "raise_softirq"
            }
           ],
           "label": "__call_rcu",
           "size": 1,
           "sourcefile": "",
           "name": "__call_rcu"
          }
         ],
         "label": "call_rcu_sched",
         "size": 1,
         "sourcefile": "",
         "name": "call_rcu_sched"
        },
        {
         "type": "original",
         "index": 2757,
         "children": [
          {
           "type": "original",
           "index": 2835,
           "children": [],
           "label": "__srcu_read_lock",
           "size": 1,
           "sourcefile": "",
           "name": "__srcu_read_lock"
          },
          {
           "type": "original",
           "index": 2836,
           "children": [],
           "label": "__srcu_read_unlock",
           "size": 1,
           "sourcefile": "",
           "name": "__srcu_read_unlock"
          }
         ],
         "label": "fsnotify",
         "size": 1,
         "sourcefile": "",
         "name": "fsnotify"
        },
        {
         "type": "original",
         "index": 2771,
         "children": [
          {
           "type": "original",
           "index": 2772,
           "children": [],
           "label": "lockref_put_or_lock",
           "size": 1,
           "sourcefile": "",
           "name": "lockref_put_or_lock"
          },
          {
           "type": "original",
           "index": 2799,
           "children": [],
           "label": "lockref_put_return",
           "size": 1,
           "sourcefile": "",
           "name": "lockref_put_return"
          },
          {
           "type": "original",
           "index": 2805,
           "children": [
            {
             "type": "original",
             "index": 2823,
             "children": [
              {
               "type": "original",
               "index": 2824,
               "children": [
                {
                 "type": "original",
                 "index": 2825,
                 "children": [],
                 "label": "fsnotify_destroy_marks",
                 "size": 1,
                 "sourcefile": "",
                 "name": "fsnotify_destroy_marks"
                }
               ],
               "label": "fsnotify_clear_marks_by_inode",
               "size": 1,
               "sourcefile": "",
               "name": "fsnotify_clear_marks_by_inode"
              }
             ],
             "label": "__fsnotify_inode_delete",
             "size": 1,
             "sourcefile": "",
             "name": "__fsnotify_inode_delete"
            },
            {
             "type": "original",
             "index": 2807,
             "children": [],
             "label": "__d_drop",
             "size": 1,
             "sourcefile": "",
             "name": "__d_drop"
            },
            {
             "type": "original",
             "index": 2806,
             "children": [],
             "label": "lockref_mark_dead",
             "size": 1,
             "sourcefile": "",
             "name": "lockref_mark_dead"
            },
            {
             "type": "original",
             "index": 2808,
             "children": [
              {
               "type": "original",
               "index": 2809,
               "children": [],
               "label": "_atomic_dec_and_lock",
               "size": 1,
               "sourcefile": "",
               "name": "_atomic_dec_and_lock"
              },
              {
               "type": "original",
               "index": 2810,
               "children": [
                {
                 "type": "original",
                 "index": 2815,
                 "children": [],
                 "label": "clear_inode",
                 "size": 1,
                 "sourcefile": "",
                 "name": "clear_inode"
                },
                {
                 "type": "original",
                 "index": 2816,
                 "children": [
                  {
                   "type": "original",
                   "index": 2817,
                   "children": [],
                   "label": "__wake_up_bit",
                   "size": 1,
                   "sourcefile": "",
                   "name": "__wake_up_bit"
                  }
                 ],
                 "label": "wake_up_bit",
                 "size": 1,
                 "sourcefile": "",
                 "name": "wake_up_bit"
                },
                {
                 "type": "original",
                 "index": 2818,
                 "children": [
                  {
                   "type": "original",
                   "index": 2819,
                   "children": [
                    {
                     "type": "original",
                     "index": 2821,
                     "children": [
                      {
                       "type": "original",
                       "index": 2822,
                       "children": [],
                       "label": "integrity_inode_free",
                       "size": 1,
                       "sourcefile": "",
                       "name": "integrity_inode_free"
                      }
                     ],
                     "label": "security_inode_free",
                     "size": 1,
                     "sourcefile": "",
                     "name": "security_inode_free"
                    },
                    {
                     "type": "original",
                     "index": 2820,
                     "children": [],
                     "label": "inode_has_buffers",
                     "size": 1,
                     "sourcefile": "",
                     "name": "inode_has_buffers"
                    },
                    {
                     "type": "original",
                     "index": 2826,
                     "children": [],
                     "label": "locks_free_lock_context",
                     "size": 1,
                     "sourcefile": "",
                     "name": "locks_free_lock_context"
                    }
                   ],
                   "label": "__destroy_inode",
                   "size": 1,
                   "sourcefile": "",
                   "name": "__destroy_inode"
                  }
                 ],
                 "label": "destroy_inode",
                 "size": 1,
                 "sourcefile": "",
                 "name": "destroy_inode"
                },
                {
                 "type": "original",
                 "index": 2814,
                 "children": [],
                 "label": "truncate_inode_pages_final",
                 "size": 1,
                 "sourcefile": "",
                 "name": "truncate_inode_pages_final"
                },
                {
                 "type": "original",
                 "index": 2811,
                 "children": [
                  {
                   "type": "original",
                   "index": 2812,
                   "children": [
                    {
                     "type": "original",
                     "index": 2813,
                     "children": [],
                     "label": "bit_waitqueue",
                     "size": 1,
                     "sourcefile": "",
                     "name": "bit_waitqueue"
                    }
                   ],
                   "label": "__inode_wait_for_writeback",
                   "size": 1,
                   "sourcefile": "",
                   "name": "__inode_wait_for_writeback"
                  }
                 ],
                 "label": "inode_wait_for_writeback",
                 "size": 1,
                 "sourcefile": "",
                 "name": "inode_wait_for_writeback"
                }
               ],
               "label": "evict",
               "size": 1,
               "sourcefile": "",
               "name": "evict"
              }
             ],
             "label": "iput",
             "size": 1,
             "sourcefile": "",
             "name": "iput"
            },
            {
             "type": "original",
             "index": 2827,
             "children": [],
             "label": "dentry_free",
             "size": 1,
             "sourcefile": "",
             "name": "dentry_free"
            }
           ],
           "label": "__dentry_kill",
           "size": 1,
           "sourcefile": "",
           "name": "__dentry_kill"
          }
         ],
         "label": "dput",
         "size": 1,
         "sourcefile": "",
         "name": "dput"
        },
        {
         "type": "original",
         "index": 2758,
         "children": [
          {
           "type": "original",
           "index": 2786,
           "children": [],
           "label": "locks_remove_posix",
           "size": 1,
           "sourcefile": "",
           "name": "locks_remove_posix"
          }
         ],
         "label": "locks_remove_file",
         "size": 1,
         "sourcefile": "",
         "name": "locks_remove_file"
        },
        {
         "type": "original",
         "index": 2761,
         "children": [],
         "label": "module_put",
         "size": 1,
         "sourcefile": "",
         "name": "module_put"
        },
        {
         "type": "original",
         "index": 2762,
         "children": [
          {
           "type": "original",
           "index": 2833,
           "children": [],
           "label": "put_pid_ns",
           "size": 1,
           "sourcefile": "",
           "name": "put_pid_ns"
          },
          {
           "type": "original",
           "index": 2775,
           "children": [],
           "label": "kmem_cache_free",
           "size": 1,
           "sourcefile": "",
           "name": "kmem_cache_free"
          }
         ],
         "label": "put_pid",
         "size": 1,
         "sourcefile": "",
         "name": "put_pid"
        },
        {
         "type": "original",
         "index": 2763,
         "children": [],
         "label": "__percpu_counter_add",
         "size": 1,
         "sourcefile": "",
         "name": "__percpu_counter_add"
        },
        {
         "type": "original",
         "index": 2773,
         "children": [
          {
           "type": "original",
           "index": 2774,
           "children": [],
           "label": "mntput_no_expire",
           "size": 1,
           "sourcefile": "",
           "name": "mntput_no_expire"
          }
         ],
         "label": "mntput",
         "size": 1,
         "sourcefile": "",
         "name": "mntput"
        }
       ],
       "label": "__fput",
       "size": 1,
       "sourcefile": "",
       "name": "__fput"
      }
     ],
     "label": "____fput",
     "size": 1,
     "sourcefile": "",
     "name": "____fput"
    },
    {
     "type": "original",
     "index": 2750,
     "children": [
      {
       "type": "original",
       "index": 2751,
       "children": [],
       "label": "kick_process",
       "size": 1,
       "sourcefile": "",
       "name": "kick_process"
      }
     ],
     "label": "task_work_add",
     "size": 1,
     "sourcefile": "",
     "name": "task_work_add"
    }
   ],
   "label": "fput",
   "size": 1,
   "sourcefile": "",
   "name": "fput"
  },
  {
   "type": "original",
   "index": 2699,
   "children": [
    {
     "type": "original",
     "index": 2700,
     "children": [
      {
       "type": "original",
       "index": 2704,
       "children": [
        {
         "type": "original",
         "index": 2752,
         "children": [],
         "label": "next_zones_zonelist",
         "size": 1,
         "sourcefile": "",
         "name": "next_zones_zonelist"
        },
        {
         "type": "original",
         "index": 2753,
         "children": [],
         "label": "__cpuset_node_allowed",
         "size": 1,
         "sourcefile": "",
         "name": "__cpuset_node_allowed"
        },
        {
         "type": "original",
         "index": 2837,
         "children": [],
         "label": "get_partial_node",
         "size": 1,
         "sourcefile": "",
         "name": "get_partial_node"
        },
        {
         "type": "original",
         "index": 2705,
         "children": [],
         "label": "__cmpxchg_double_slab",
         "size": 1,
         "sourcefile": "",
         "name": "__cmpxchg_double_slab"
        }
       ],
       "label": "__slab_alloc",
       "size": 1,
       "sourcefile": "",
       "name": "__slab_alloc"
      },
      {
       "type": "original",
       "index": 2744,
       "children": [],
       "label": "memset",
       "size": 1,
       "sourcefile": "",
       "name": "memset"
      },
      {
       "type": "original",
       "index": 2702,
       "children": [
        {
         "type": "original",
         "index": 2703,
         "children": [
          {
           "type": "original",
           "index": 2706,
           "children": [
            {
             "type": "original",
             "index": 2738,
             "children": [
              {
               "type": "original",
               "index": 2739,
               "children": [],
               "label": "enqueue_task",
               "size": 1,
               "sourcefile": "",
               "name": "enqueue_task"
              }
             ],
             "label": "activate_task",
             "size": 1,
             "sourcefile": "",
             "name": "activate_task"
            },
            {
             "type": "original",
             "index": 2719,
             "children": [],
             "label": "rcu_note_context_switch",
             "size": 1,
             "sourcefile": "",
             "name": "rcu_note_context_switch"
            },
            {
             "type": "original",
             "index": 2708,
             "children": [
              {
               "type": "original",
               "index": 2709,
               "children": [
                {
                 "type": "original",
                 "index": 2710,
                 "children": [],
                 "label": "sched_clock",
                 "size": 1,
                 "sourcefile": "",
                 "name": "sched_clock"
                }
               ],
               "label": "sched_clock_cpu",
               "size": 1,
               "sourcefile": "",
               "name": "sched_clock_cpu"
              }
             ],
             "label": "update_rq_clock",
             "size": 1,
             "sourcefile": "",
             "name": "update_rq_clock"
            },
            {
             "type": "original",
             "index": 2797,
             "children": [],
             "label": "_raw_spin_trylock",
             "size": 1,
             "sourcefile": "",
             "name": "_raw_spin_trylock"
            },
            {
             "type": "original",
             "index": 2729,
             "children": [
              {
               "type": "original",
               "index": 2730,
               "children": [
                {
                 "type": "original",
                 "index": 2731,
                 "children": [
                  {
                   "type": "original",
                   "index": 2732,
                   "children": [
                    {
                     "type": "original",
                     "index": 2733,
                     "children": [
                      {
                       "type": "original",
                       "index": 2734,
                       "children": [
                        {
                         "type": "original",
                         "index": 2735,
                         "children": [],
                         "label": "event_sched_in",
                         "size": 1,
                         "sourcefile": "",
                         "name": "event_sched_in"
                        }
                       ],
                       "label": "group_sched_in",
                       "size": 1,
                       "sourcefile": "",
                       "name": "group_sched_in"
                      },
                      {
                       "type": "original",
                       "index": 2800,
                       "children": [],
                       "label": "update_group_times",
                       "size": 1,
                       "sourcefile": "",
                       "name": "update_group_times"
                      }
                     ],
                     "label": "ctx_sched_in",
                     "size": 1,
                     "sourcefile": "",
                     "name": "ctx_sched_in"
                    }
                   ],
                   "label": "perf_event_sched_in",
                   "size": 1,
                   "sourcefile": "",
                   "name": "perf_event_sched_in"
                  },
                  {
                   "type": "original",
                   "index": 2737,
                   "children": [],
                   "label": "perf_ctx_unlock",
                   "size": 1,
                   "sourcefile": "",
                   "name": "perf_ctx_unlock"
                  }
                 ],
                 "label": "perf_event_context_sched_in",
                 "size": 1,
                 "sourcefile": "",
                 "name": "perf_event_context_sched_in"
                }
               ],
               "label": "__perf_event_task_sched_in",
               "size": 1,
               "sourcefile": "",
               "name": "__perf_event_task_sched_in"
              },
              {
               "type": "original",
               "index": 2787,
               "children": [
                {
                 "type": "original",
                 "index": 2788,
                 "children": [
                  {
                   "type": "original",
                   "index": 2789,
                   "children": [
                    {
                     "type": "original",
                     "index": 2790,
                     "children": [
                      {
                       "type": "original",
                       "index": 2791,
                       "children": [
                        {
                         "type": "original",
                         "index": 2793,
                         "children": [],
                         "label": "get_pfnblock_flags_mask",
                         "size": 1,
                         "sourcefile": "",
                         "name": "get_pfnblock_flags_mask"
                        },
                        {
                         "type": "original",
                         "index": 2792,
                         "children": [],
                         "label": "free_pages_prepare",
                         "size": 1,
                         "sourcefile": "",
                         "name": "free_pages_prepare"
                        }
                       ],
                       "label": "free_hot_cold_page",
                       "size": 1,
                       "sourcefile": "",
                       "name": "free_hot_cold_page"
                      }
                     ],
                     "label": "__free_pages",
                     "size": 1,
                     "sourcefile": "",
                     "name": "__free_pages"
                    }
                   ],
                   "label": "free_pages",
                   "size": 1,
                   "sourcefile": "",
                   "name": "free_pages"
                  }
                 ],
                 "label": "pgd_free",
                 "size": 1,
                 "sourcefile": "",
                 "name": "pgd_free"
                },
                {
                 "type": "original",
                 "index": 2794,
                 "children": [
                  {
                   "type": "original",
                   "index": 2795,
                   "children": [],
                   "label": "free_ldt_struct",
                   "size": 1,
                   "sourcefile": "",
                   "name": "free_ldt_struct"
                  }
                 ],
                 "label": "destroy_context",
                 "size": 1,
                 "sourcefile": "",
                 "name": "destroy_context"
                }
               ],
               "label": "__mmdrop",
               "size": 1,
               "sourcefile": "",
               "name": "__mmdrop"
              }
             ],
             "label": "finish_task_switch",
             "size": 1,
             "sourcefile": "",
             "name": "finish_task_switch"
            },
            {
             "type": "original",
             "index": 2743,
             "children": [],
             "label": "ttwu_stat",
             "size": 1,
             "sourcefile": "",
             "name": "ttwu_stat"
            },
            {
             "type": "original",
             "index": 2776,
             "children": [
              {
               "type": "original",
               "index": 2777,
               "children": [
                {
                 "type": "original",
                 "index": 2778,
                 "children": [
                  {
                   "type": "original",
                   "index": 2782,
                   "children": [],
                   "label": "__hrtimer_get_next_event",
                   "size": 1,
                   "sourcefile": "",
                   "name": "__hrtimer_get_next_event"
                  },
                  {
                   "type": "original",
                   "index": 2783,
                   "children": [
                    {
                     "type": "original",
                     "index": 2784,
                     "children": [
                      {
                       "type": "original",
                       "index": 2785,
                       "children": [],
                       "label": "ktime_get",
                       "size": 1,
                       "sourcefile": "",
                       "name": "ktime_get"
                      }
                     ],
                     "label": "clockevents_program_event",
                     "size": 1,
                     "sourcefile": "",
                     "name": "clockevents_program_event"
                    }
                   ],
                   "label": "tick_program_event",
                   "size": 1,
                   "sourcefile": "",
                   "name": "tick_program_event"
                  },
                  {
                   "type": "original",
                   "index": 2779,
                   "children": [
                    {
                     "type": "original",
                     "index": 2781,
                     "children": [],
                     "label": "rb_erase",
                     "size": 1,
                     "sourcefile": "",
                     "name": "rb_erase"
                    },
                    {
                     "type": "original",
                     "index": 2780,
                     "children": [],
                     "label": "rb_next",
                     "size": 1,
                     "sourcefile": "",
                     "name": "rb_next"
                    }
                   ],
                   "label": "timerqueue_del",
                   "size": 1,
                   "sourcefile": "",
                   "name": "timerqueue_del"
                  }
                 ],
                 "label": "__remove_hrtimer",
                 "size": 1,
                 "sourcefile": "",
                 "name": "__remove_hrtimer"
                }
               ],
               "label": "hrtimer_try_to_cancel",
               "size": 1,
               "sourcefile": "",
               "name": "hrtimer_try_to_cancel"
              }
             ],
             "label": "hrtimer_cancel",
             "size": 1,
             "sourcefile": "",
             "name": "hrtimer_cancel"
            },
            {
             "type": "original",
             "index": 2711,
             "children": [],
             "label": "hrtimer_active",
             "size": 1,
             "sourcefile": "",
             "name": "hrtimer_active"
            },
            {
             "type": "original",
             "index": 2740,
             "children": [
              {
               "type": "original",
               "index": 2741,
               "children": [
                {
                 "type": "original",
                 "index": 2742,
                 "children": [],
                 "label": "resched_curr",
                 "size": 1,
                 "sourcefile": "",
                 "name": "resched_curr"
                }
               ],
               "label": "check_preempt_curr",
               "size": 1,
               "sourcefile": "",
               "name": "check_preempt_curr"
              }
             ],
             "label": "ttwu_do_wakeup",
             "size": 1,
             "sourcefile": "",
             "name": "ttwu_do_wakeup"
            },
            {
             "type": "original",
             "index": 2720,
             "children": [],
             "label": "___perf_sw_event",
             "size": 1,
             "sourcefile": "",
             "name": "___perf_sw_event"
            },
            {
             "type": "original",
             "index": 2802,
             "children": [
              {
               "type": "original",
               "index": 2803,
               "children": [],
               "label": "dequeue_task",
               "size": 1,
               "sourcefile": "",
               "name": "dequeue_task"
              }
             ],
             "label": "deactivate_task",
             "size": 1,
             "sourcefile": "",
             "name": "deactivate_task"
            },
            {
             "type": "original",
             "index": 2707,
             "children": [],
             "label": "_raw_spin_lock",
             "size": 1,
             "sourcefile": "",
             "name": "_raw_spin_lock"
            },
            {
             "type": "original",
             "index": 2831,
             "children": [
              {
               "type": "original",
               "index": 2832,
               "children": [],
               "label": "kthread_data",
               "size": 1,
               "sourcefile": "",
               "name": "kthread_data"
              }
             ],
             "label": "wq_worker_waking_up",
             "size": 1,
             "sourcefile": "",
             "name": "wq_worker_waking_up"
            },
            {
             "type": "original",
             "index": 2712,
             "children": [],
             "label": "_raw_spin_lock_irq",
             "size": 1,
             "sourcefile": "",
             "name": "_raw_spin_lock_irq"
            },
            {
             "type": "original",
             "index": 2721,
             "children": [
              {
               "type": "original",
               "index": 2722,
               "children": [
                {
                 "type": "original",
                 "index": 2724,
                 "children": [],
                 "label": "perf_pmu_disable",
                 "size": 1,
                 "sourcefile": "",
                 "name": "perf_pmu_disable"
                },
                {
                 "type": "original",
                 "index": 2725,
                 "children": [
                  {
                   "type": "original",
                   "index": 2726,
                   "children": [],
                   "label": "event_sched_out",
                   "size": 1,
                   "sourcefile": "",
                   "name": "event_sched_out"
                  }
                 ],
                 "label": "group_sched_out",
                 "size": 1,
                 "sourcefile": "",
                 "name": "group_sched_out"
                },
                {
                 "type": "original",
                 "index": 2727,
                 "children": [],
                 "label": "perf_pmu_enable",
                 "size": 1,
                 "sourcefile": "",
                 "name": "perf_pmu_enable"
                }
               ],
               "label": "ctx_sched_out",
               "size": 1,
               "sourcefile": "",
               "name": "ctx_sched_out"
              },
              {
               "type": "original",
               "index": 2723,
               "children": [],
               "label": "local_clock",
               "size": 1,
               "sourcefile": "",
               "name": "local_clock"
              },
              {
               "type": "original",
               "index": 2736,
               "children": [],
               "label": "perf_event_update_userpage",
               "size": 1,
               "sourcefile": "",
               "name": "perf_event_update_userpage"
              },
              {
               "type": "original",
               "index": 2801,
               "children": [],
               "label": "update_event_times",
               "size": 1,
               "sourcefile": "",
               "name": "update_event_times"
              },
              {
               "type": "original",
               "index": 2804,
               "children": [],
               "label": "perf_cgroup_switch",
               "size": 1,
               "sourcefile": "",
               "name": "perf_cgroup_switch"
              }
             ],
             "label": "__perf_event_task_sched_out",
             "size": 1,
             "sourcefile": "",
             "name": "__perf_event_task_sched_out"
            },
            {
             "type": "original",
             "index": 2728,
             "children": [],
             "label": "__switch_to",
             "size": 1,
             "sourcefile": "",
             "name": "__switch_to"
            }
           ],
           "label": "__schedule",
           "size": 1,
           "sourcefile": "",
           "name": "__schedule"
          }
         ],
         "label": "preempt_schedule_common",
         "size": 1,
         "sourcefile": "",
         "name": "preempt_schedule_common"
        }
       ],
       "label": "_cond_resched",
       "size": 1,
       "sourcefile": "",
       "name": "_cond_resched"
      },
      {
       "type": "original",
       "index": 2701,
       "children": [],
       "label": "kmalloc_slab",
       "size": 1,
       "sourcefile": "",
       "name": "kmalloc_slab"
      }
     ],
     "label": "__kmalloc",
     "size": 1,
     "sourcefile": "",
     "name": "__kmalloc"
    },
    {
     "type": "original",
     "index": 2745,
     "children": [],
     "label": "_copy_to_user",
     "size": 1,
     "sourcefile": "",
     "name": "_copy_to_user"
    },
    {
     "type": "original",
     "index": 2746,
     "children": [
      {
       "type": "original",
       "index": 2747,
       "children": [],
       "label": "security_inode_listxattr",
       "size": 1,
       "sourcefile": "",
       "name": "security_inode_listxattr"
      },
      {
       "type": "original",
       "index": 2748,
       "children": [],
       "label": "security_inode_listsecurity",
       "size": 1,
       "sourcefile": "",
       "name": "security_inode_listsecurity"
      }
     ],
     "label": "vfs_listxattr",
     "size": 1,
     "sourcefile": "",
     "name": "vfs_listxattr"
    },
    {
     "type": "original",
     "index": 2713,
     "children": [
      {
       "type": "original",
       "index": 2714,
       "children": [
        {
         "type": "original",
         "index": 2716,
         "children": [],
         "label": "_raw_spin_lock_irqsave",
         "size": 1,
         "sourcefile": "",
         "name": "_raw_spin_lock_irqsave"
        },
        {
         "type": "original",
         "index": 2718,
         "children": [],
         "label": "put_cpu_partial",
         "size": 1,
         "sourcefile": "",
         "name": "put_cpu_partial"
        },
        {
         "type": "original",
         "index": 2717,
         "children": [],
         "label": "_raw_spin_unlock_irqrestore",
         "size": 1,
         "sourcefile": "",
         "name": "_raw_spin_unlock_irqrestore"
        },
        {
         "type": "original",
         "index": 2715,
         "children": [],
         "label": "cmpxchg_double_slab",
         "size": 1,
         "sourcefile": "",
         "name": "cmpxchg_double_slab"
        }
       ],
       "label": "__slab_free",
       "size": 1,
       "sourcefile": "",
       "name": "__slab_free"
      }
     ],
     "label": "kfree",
     "size": 1,
     "sourcefile": "",
     "name": "kfree"
    }
   ],
   "label": "listxattr",
   "size": 1,
   "sourcefile": "",
   "name": "listxattr"
  },
  {
   "type": "original",
   "index": 2697,
   "children": [
    {
     "type": "original",
     "index": 2698,
     "children": [],
     "label": "__fget_light",
     "size": 1,
     "sourcefile": "",
     "name": "__fget_light"
    }
   ],
   "label": "__fdget",
   "size": 1,
   "sourcefile": "",
   "name": "__fdget"
  }
 ],
 "label": "sys_flistxattr",
 "size": 1,
 "sourcefile": "",
 "name": "sys_flistxattr"
}